[
    [
        [
            [
                1.0,
                1.0,
                1.0
            ]
        ],
        -3.0748877784489452,
        [
            {
                "onsite0": [
                    {
                        "Em": 1.1711470240441464,
                        "num_trials": 100000,
                        "post-processed": 25370,
                        "params": [
                            [
                                0.58,
                                0.567,
                                0.678
                            ]
                        ],
                        "grad": 0,
                        "sgn": 0
                    },
                    {
                        "Em": 1.2561622918635935,
                        "num_trials": 100000,
                        "post-processed": 27506,
                        "params": [
                            [
                                -0.58,
                                -0.567,
                                -0.678
                            ]
                        ],
                        "grad": 1,
                        "sgn": 0
                    },
                    {
                        "Em": 2.054817080343489,
                        "num_trials": 100000,
                        "post-processed": 25503,
                        "params": [
                            [
                                0.0,
                                0.567,
                                0.678
                            ]
                        ],
                        "grad": 2,
                        "sgn": 0
                    },
                    {
                        "Em": 2.108610492357324,
                        "num_trials": 100000,
                        "post-processed": 26038,
                        "params": [
                            [
                                0.0,
                                -0.567,
                                -0.678
                            ]
                        ],
                        "grad": 3,
                        "sgn": 0
                    }
                ],
                "horiz0": [
                    {
                        "Em": -2.0707813301419047,
                        "num_trials": 100000,
                        "post-processed": 23396,
                        "params": [
                            [
                                0.58,
                                0.567,
                                0.678
                            ]
                        ],
                        "grad": 0,
                        "sgn": 0
                    },
                    {
                        "Em": -2.3388474681578133,
                        "num_trials": 100000,
                        "post-processed": 25752,
                        "params": [
                            [
                                -0.58,
                                -0.567,
                                -0.678
                            ]
                        ],
                        "grad": 1,
                        "sgn": 0
                    },
                    {
                        "Em": -2.399273387829246,
                        "num_trials": 100000,
                        "post-processed": 22020,
                        "params": [
                            [
                                0.0,
                                0.567,
                                0.678
                            ]
                        ],
                        "grad": 2,
                        "sgn": 0
                    },
                    {
                        "Em": -2.4253360784788667,
                        "num_trials": 100000,
                        "post-processed": 24771,
                        "params": [
                            [
                                0.0,
                                -0.567,
                                -0.678
                            ]
                        ],
                        "grad": 3,
                        "sgn": 0
                    }
                ],
                "horiz1": [
                    {
                        "Em": -2.058911377480841,
                        "num_trials": 100000,
                        "post-processed": 25445,
                        "params": [
                            [
                                0.58,
                                0.567,
                                0.678
                            ]
                        ],
                        "grad": 0,
                        "sgn": 0
                    },
                    {
                        "Em": -2.1085446970250716,
                        "num_trials": 100000,
                        "post-processed": 27362,
                        "params": [
                            [
                                -0.58,
                                -0.567,
                                -0.678
                            ]
                        ],
                        "grad": 1,
                        "sgn": 0
                    },
                    {
                        "Em": -2.358025164953199,
                        "num_trials": 100000,
                        "post-processed": 26068,
                        "params": [
                            [
                                0.0,
                                0.567,
                                0.678
                            ]
                        ],
                        "grad": 2,
                        "sgn": 0
                    },
                    {
                        "Em": -2.3385723885611887,
                        "num_trials": 100000,
                        "post-processed": 26786,
                        "params": [
                            [
                                0.0,
                                -0.567,
                                -0.678
                            ]
                        ],
                        "grad": 3,
                        "sgn": 0
                    }
                ],
                "all_E": {
                    "0": {
                        "0": -2.958545683578599
                    },
                    "1": {
                        "0": -3.1912298733192914
                    },
                    "2": {
                        "0": -2.702481472438956
                    },
                    "3": {
                        "0": -2.6552979746827314
                    }
                },
                "start_timestamp": "2021-09-14 00:56:38.937086",
                "end_timestamp": "2021-09-14 00:57:37.384421",
                "program_id": "8x1_single_zz_x_U_4_nocc_4_d_1-0914-005628-005638-937128",
                "job_id": "8x1_single_zz_x_U_4_nocc_4_d_1-0914-005628",
                "E": -3.0748877784489452,
                "E_list": [
                    -2.958545683578599,
                    -3.1912298733192914,
                    -2.702481472438956,
                    -2.6552979746827314
                ]
            }
        ],
        [
            -3.0748877784489452
        ],
        [
            [
                [
                    [
                        0.58,
                        0.567,
                        0.678
                    ]
                ]
            ],
            [
                [
                    [
                        -0.58,
                        -0.567,
                        -0.678
                    ]
                ]
            ],
            [
                [
                    [
                        0,
                        0.567,
                        0.678
                    ]
                ]
            ],
            [
                [
                    [
                        0,
                        -0.567,
                        -0.678
                    ]
                ]
            ]
        ],
        0
    ]
]