[
    [
        [
            [
                1.0,
                1.0,
                1.0
            ]
        ],
        3.458972069043439,
        [
            {
                "onsite0": [
                    {
                        "Em": 8.097008159564822,
                        "num_trials": 100000,
                        "post-processed": 22060,
                        "params": [
                            [
                                0.605,
                                0.655,
                                0.466
                            ]
                        ],
                        "grad": 0,
                        "sgn": 0
                    },
                    {
                        "Em": 8.846805105092457,
                        "num_trials": 100000,
                        "post-processed": 23741,
                        "params": [
                            [
                                -0.605,
                                -0.655,
                                -0.466
                            ]
                        ],
                        "grad": 1,
                        "sgn": 0
                    },
                    {
                        "Em": 9.703397784869534,
                        "num_trials": 100000,
                        "post-processed": 21308,
                        "params": [
                            [
                                0.0,
                                0.655,
                                0.466
                            ]
                        ],
                        "grad": 2,
                        "sgn": 0
                    },
                    {
                        "Em": 10.57831963954413,
                        "num_trials": 100000,
                        "post-processed": 22638,
                        "params": [
                            [
                                0.0,
                                -0.655,
                                -0.466
                            ]
                        ],
                        "grad": 3,
                        "sgn": 0
                    }
                ],
                "horiz0": [
                    {
                        "Em": -2.7560162721168453,
                        "num_trials": 100000,
                        "post-processed": 20403,
                        "params": [
                            [
                                0.605,
                                0.655,
                                0.466
                            ]
                        ],
                        "grad": 0,
                        "sgn": 0
                    },
                    {
                        "Em": -3.8924716972820574,
                        "num_trials": 100000,
                        "post-processed": 22701,
                        "params": [
                            [
                                -0.605,
                                -0.655,
                                -0.466
                            ]
                        ],
                        "grad": 1,
                        "sgn": 0
                    },
                    {
                        "Em": -3.5725823591923485,
                        "num_trials": 100000,
                        "post-processed": 18820,
                        "params": [
                            [
                                0.0,
                                0.655,
                                0.466
                            ]
                        ],
                        "grad": 2,
                        "sgn": 0
                    },
                    {
                        "Em": -3.9662718962489305,
                        "num_trials": 100000,
                        "post-processed": 22207,
                        "params": [
                            [
                                0.0,
                                -0.655,
                                -0.466
                            ]
                        ],
                        "grad": 3,
                        "sgn": 0
                    }
                ],
                "horiz1": [
                    {
                        "Em": -1.7600901916572715,
                        "num_trials": 100000,
                        "post-processed": 22175,
                        "params": [
                            [
                                0.605,
                                0.655,
                                0.466
                            ]
                        ],
                        "grad": 0,
                        "sgn": 0
                    },
                    {
                        "Em": -1.6172909655142271,
                        "num_trials": 100000,
                        "post-processed": 22879,
                        "params": [
                            [
                                -0.605,
                                -0.655,
                                -0.466
                            ]
                        ],
                        "grad": 1,
                        "sgn": 0
                    },
                    {
                        "Em": -2.0655926352128886,
                        "num_trials": 100000,
                        "post-processed": 21725,
                        "params": [
                            [
                                0.0,
                                0.655,
                                0.466
                            ]
                        ],
                        "grad": 2,
                        "sgn": 0
                    },
                    {
                        "Em": -1.8180098539503784,
                        "num_trials": 100000,
                        "post-processed": 22732,
                        "params": [
                            [
                                0.0,
                                -0.655,
                                -0.466
                            ]
                        ],
                        "grad": 3,
                        "sgn": 0
                    }
                ],
                "all_E": {
                    "0": {
                        "0": 3.580901695790706
                    },
                    "1": {
                        "0": 3.3370424422961724
                    },
                    "2": {
                        "0": 4.065222790464297
                    },
                    "3": {
                        "0": 4.794037889344821
                    }
                },
                "start_timestamp": "2021-09-14 03:21:31.418375",
                "end_timestamp": "2021-09-14 03:22:23.387223",
                "program_id": "8x1_single_zz_x_U_4_nocc_9_d_1-0914-032121-032131-418422",
                "job_id": "8x1_single_zz_x_U_4_nocc_9_d_1-0914-032121",
                "E": 3.458972069043439,
                "E_list": [
                    3.580901695790706,
                    3.3370424422961724,
                    4.065222790464297,
                    4.794037889344821
                ]
            }
        ],
        [
            3.458972069043439
        ],
        [
            [
                [
                    [
                        0.605,
                        0.655,
                        0.466
                    ]
                ]
            ],
            [
                [
                    [
                        -0.605,
                        -0.655,
                        -0.466
                    ]
                ]
            ],
            [
                [
                    [
                        0,
                        0.655,
                        0.466
                    ]
                ]
            ],
            [
                [
                    [
                        0,
                        -0.655,
                        -0.466
                    ]
                ]
            ]
        ],
        0
    ]
]