[
    [
        [
            [
                1.0,
                1.0,
                1.0,
                1.0
            ]
        ],
        8.98828,
        [
            {
                "onsite0": [
                    {
                        "Em": 17.05124,
                        "num_trials": 100000,
                        "post-processed": 100000,
                        "params": [
                            [
                                0.439,
                                0.373,
                                0.576,
                                0.473
                            ]
                        ],
                        "grad": 0,
                        "sgn": 0
                    },
                    {
                        "Em": 17.06148,
                        "num_trials": 100000,
                        "post-processed": 100000,
                        "params": [
                            [
                                -0.439,
                                -0.373,
                                -0.576,
                                -0.473
                            ]
                        ],
                        "grad": 1,
                        "sgn": 0
                    },
                    {
                        "Em": 18.01768,
                        "num_trials": 100000,
                        "post-processed": 100000,
                        "params": [
                            [
                                0.0,
                                0.373,
                                0.576,
                                0.473
                            ]
                        ],
                        "grad": 2,
                        "sgn": 0
                    },
                    {
                        "Em": 18.00376,
                        "num_trials": 100000,
                        "post-processed": 100000,
                        "params": [
                            [
                                0.0,
                                -0.373,
                                -0.576,
                                -0.473
                            ]
                        ],
                        "grad": 3,
                        "sgn": 0
                    }
                ],
                "horiz0": [
                    {
                        "Em": -3.8039399999999994,
                        "num_trials": 100000,
                        "post-processed": 100000,
                        "params": [
                            [
                                0.439,
                                0.373,
                                0.576,
                                0.473
                            ]
                        ],
                        "grad": 0,
                        "sgn": 0
                    },
                    {
                        "Em": -3.80278,
                        "num_trials": 100000,
                        "post-processed": 100000,
                        "params": [
                            [
                                -0.439,
                                -0.373,
                                -0.576,
                                -0.473
                            ]
                        ],
                        "grad": 1,
                        "sgn": 0
                    },
                    {
                        "Em": -3.9910799999999997,
                        "num_trials": 100000,
                        "post-processed": 100000,
                        "params": [
                            [
                                0.0,
                                0.373,
                                0.576,
                                0.473
                            ]
                        ],
                        "grad": 2,
                        "sgn": 0
                    },
                    {
                        "Em": -3.99062,
                        "num_trials": 100000,
                        "post-processed": 100000,
                        "params": [
                            [
                                0.0,
                                -0.373,
                                -0.576,
                                -0.473
                            ]
                        ],
                        "grad": 3,
                        "sgn": 0
                    }
                ],
                "vert02": [
                    {
                        "Em": -2.02311,
                        "num_trials": 100000,
                        "post-processed": 100000,
                        "params": [
                            [
                                0.439,
                                0.373,
                                0.576,
                                0.473
                            ]
                        ],
                        "grad": 0,
                        "sgn": 0
                    },
                    {
                        "Em": -2.03109,
                        "num_trials": 100000,
                        "post-processed": 100000,
                        "params": [
                            [
                                -0.439,
                                -0.373,
                                -0.576,
                                -0.473
                            ]
                        ],
                        "grad": 1,
                        "sgn": 0
                    },
                    {
                        "Em": -2.11443,
                        "num_trials": 100000,
                        "post-processed": 100000,
                        "params": [
                            [
                                0.0,
                                0.373,
                                0.576,
                                0.473
                            ]
                        ],
                        "grad": 2,
                        "sgn": 0
                    },
                    {
                        "Em": -2.11082,
                        "num_trials": 100000,
                        "post-processed": 100000,
                        "params": [
                            [
                                0.0,
                                -0.373,
                                -0.576,
                                -0.473
                            ]
                        ],
                        "grad": 3,
                        "sgn": 0
                    }
                ],
                "vert12": [
                    {
                        "Em": -2.2385,
                        "num_trials": 100000,
                        "post-processed": 100000,
                        "params": [
                            [
                                0.439,
                                0.373,
                                0.576,
                                0.473
                            ]
                        ],
                        "grad": 0,
                        "sgn": 0
                    },
                    {
                        "Em": -2.23674,
                        "num_trials": 100000,
                        "post-processed": 100000,
                        "params": [
                            [
                                -0.439,
                                -0.373,
                                -0.576,
                                -0.473
                            ]
                        ],
                        "grad": 1,
                        "sgn": 0
                    },
                    {
                        "Em": -2.34273,
                        "num_trials": 100000,
                        "post-processed": 100000,
                        "params": [
                            [
                                0.0,
                                0.373,
                                0.576,
                                0.473
                            ]
                        ],
                        "grad": 2,
                        "sgn": 0
                    },
                    {
                        "Em": -2.34314,
                        "num_trials": 100000,
                        "post-processed": 100000,
                        "params": [
                            [
                                0.0,
                                -0.373,
                                -0.576,
                                -0.473
                            ]
                        ],
                        "grad": 3,
                        "sgn": 0
                    }
                ],
                "all_E": {
                    "0": {
                        "0": 8.98569
                    },
                    "1": {
                        "0": 8.990869999999997
                    },
                    "2": {
                        "0": 9.569439999999998
                    },
                    "3": {
                        "0": 9.55918
                    }
                },
                "start_timestamp": "2021-12-11 22:27:35.657923",
                "end_timestamp": "2021-12-11 22:28:14.959780",
                "E": 8.98828,
                "E_list": [
                    8.98569,
                    8.990869999999997,
                    9.569439999999998,
                    9.55918
                ]
            }
        ],
        [
            8.98828
        ],
        [
            [
                [
                    [
                        0.439,
                        0.373,
                        0.576,
                        0.473
                    ]
                ]
            ],
            [
                [
                    [
                        -0.439,
                        -0.373,
                        -0.576,
                        -0.473
                    ]
                ]
            ],
            [
                [
                    [
                        0,
                        0.373,
                        0.576,
                        0.473
                    ]
                ]
            ],
            [
                [
                    [
                        0,
                        -0.373,
                        -0.576,
                        -0.473
                    ]
                ]
            ]
        ],
        0
    ]
]