[
    [
        [
            [
                1.0,
                1.0,
                1.0,
                1.0
            ]
        ],
        [
            -5.156678080558777,
            -5.484803080558777,
            -5.556284189224243,
            -6.037197709083557,
            -6.302040696144104,
            -6.408449649810791,
            -6.434470176696777,
            -6.446622848510742,
            -6.450981616973877,
            -6.477088451385498,
            -6.5507659912109375,
            -6.594611287117004,
            -6.624600172042847,
            -6.746664643287659,
            -6.823863863945007
        ],
        [
            {
                "onsite0": [
                    {
                        "Em": 1.7716370820999146,
                        "num_trials": 0,
                        "post-processed": [
                            0
                        ],
                        "params": [
                            [
                                0.8312871881382002,
                                1.1687128118617998,
                                0.8312871881382002,
                                1.1687128118617998
                            ]
                        ],
                        "grad": 0,
                        "sgn": 0
                    },
                    {
                        "Em": 1.7409800291061401,
                        "num_trials": 0,
                        "post-processed": [
                            0
                        ],
                        "params": [
                            [
                                0.6521668421445757,
                                0.9895924658681752,
                                1.0104075341318248,
                                1.3478331578554243
                            ]
                        ],
                        "grad": 1,
                        "sgn": 0
                    },
                    {
                        "Em": 1.5190298557281494,
                        "num_trials": 0,
                        "post-processed": [
                            0
                        ],
                        "params": [
                            [
                                0.756748859529051,
                                0.8850104484836998,
                                0.9058255167473495,
                                1.243251140470949
                            ]
                        ],
                        "grad": 2,
                        "sgn": 0
                    },
                    {
                        "Em": 1.601242184638977,
                        "num_trials": 0,
                        "post-processed": [
                            0
                        ],
                        "params": [
                            [
                                0.5789547286759542,
                                1.0628045793367966,
                                0.7280313858942526,
                                1.0654570096178522
                            ]
                        ],
                        "grad": 3,
                        "sgn": 0
                    },
                    {
                        "Em": 1.605389952659607,
                        "num_trials": 0,
                        "post-processed": [
                            0
                        ],
                        "params": [
                            [
                                0.4557909961777886,
                                0.939640846838631,
                                0.8511951183924182,
                                0.9422932771196866
                            ]
                        ],
                        "grad": 4,
                        "sgn": 0
                    },
                    {
                        "Em": 1.65449059009552,
                        "num_trials": 0,
                        "post-processed": [
                            0
                        ],
                        "params": [
                            [
                                0.35078384521062883,
                                0.8346336958714712,
                                0.9562022693595781,
                                0.8372861261525267
                            ]
                        ],
                        "grad": 5,
                        "sgn": 0
                    },
                    {
                        "Em": 1.5816972255706787,
                        "num_trials": 0,
                        "post-processed": [
                            0
                        ],
                        "params": [
                            [
                                0.387691322624682,
                                0.797726218457418,
                                0.9192947919455249,
                                0.8741936035665799
                            ]
                        ],
                        "grad": 6,
                        "sgn": 0
                    },
                    {
                        "Em": 1.598121166229248,
                        "num_trials": 0,
                        "post-processed": [
                            0
                        ],
                        "params": [
                            [
                                0.36596908334242495,
                                0.776003979175161,
                                0.9410170312277819,
                                0.8524713642843229
                            ]
                        ],
                        "grad": 7,
                        "sgn": 0
                    },
                    {
                        "Em": 1.5849708318710327,
                        "num_trials": 0,
                        "post-processed": [
                            0
                        ],
                        "params": [
                            [
                                0.3770148636259442,
                                0.7870497594586802,
                                0.9299712509442627,
                                0.8414255840008037
                            ]
                        ],
                        "grad": 8,
                        "sgn": 0
                    },
                    {
                        "Em": 1.5061589479446411,
                        "num_trials": 0,
                        "post-processed": [
                            0
                        ],
                        "params": [
                            [
                                0.41445659003579294,
                                0.7496080330488314,
                                0.8925295245344139,
                                0.8788673104106525
                            ]
                        ],
                        "grad": 9,
                        "sgn": 0
                    },
                    {
                        "Em": 1.5054389238357544,
                        "num_trials": 0,
                        "post-processed": [
                            0
                        ],
                        "params": [
                            [
                                0.36686128767155374,
                                0.7020127306845921,
                                0.8449342221701747,
                                0.9264626127748917
                            ]
                        ],
                        "grad": 10,
                        "sgn": 0
                    },
                    {
                        "Em": 1.5339053869247437,
                        "num_trials": 0,
                        "post-processed": [
                            0
                        ],
                        "params": [
                            [
                                0.30539268415900866,
                                0.6405441271720471,
                                0.7834656186576296,
                                0.9879312162874367
                            ]
                        ],
                        "grad": 11,
                        "sgn": 0
                    },
                    {
                        "Em": 1.4840435981750488,
                        "num_trials": 0,
                        "post-processed": [
                            0
                        ],
                        "params": [
                            [
                                0.33513453666379694,
                                0.6702859796768355,
                                0.7537237661528413,
                                0.9581893637826484
                            ]
                        ],
                        "grad": 12,
                        "sgn": 0
                    },
                    {
                        "Em": 1.2938975095748901,
                        "num_trials": 0,
                        "post-processed": [
                            0
                        ],
                        "params": [
                            [
                                0.4062771793011849,
                                0.5991433370394476,
                                0.6825811235154534,
                                0.8870467211452605
                            ]
                        ],
                        "grad": 13,
                        "sgn": 0
                    },
                    {
                        "Em": 1.3300871849060059,
                        "num_trials": 0,
                        "post-processed": [
                            0
                        ],
                        "params": [
                            [
                                0.3451094644389563,
                                0.537975622177219,
                                0.6214134086532248,
                                0.8258790062830319
                            ]
                        ],
                        "grad": 14,
                        "sgn": 0
                    }
                ],
                "horiz0": [
                    {
                        "Em": -3.257251739501953,
                        "num_trials": 0,
                        "post-processed": [
                            0
                        ],
                        "params": [
                            [
                                0.8312871881382002,
                                1.1687128118617998,
                                0.8312871881382002,
                                1.1687128118617998
                            ]
                        ],
                        "grad": 0,
                        "sgn": 0
                    },
                    {
                        "Em": -3.40570068359375,
                        "num_trials": 0,
                        "post-processed": [
                            0
                        ],
                        "params": [
                            [
                                0.6521668421445757,
                                0.9895924658681752,
                                1.0104075341318248,
                                1.3478331578554243
                            ]
                        ],
                        "grad": 1,
                        "sgn": 0
                    },
                    {
                        "Em": -3.3303990364074707,
                        "num_trials": 0,
                        "post-processed": [
                            0
                        ],
                        "params": [
                            [
                                0.756748859529051,
                                0.8850104484836998,
                                0.9058255167473495,
                                1.243251140470949
                            ]
                        ],
                        "grad": 2,
                        "sgn": 0
                    },
                    {
                        "Em": -3.609510660171509,
                        "num_trials": 0,
                        "post-processed": [
                            0
                        ],
                        "params": [
                            [
                                0.5789547286759542,
                                1.0628045793367966,
                                0.7280313858942526,
                                1.0654570096178522
                            ]
                        ],
                        "grad": 3,
                        "sgn": 0
                    },
                    {
                        "Em": -3.7253079414367676,
                        "num_trials": 0,
                        "post-processed": [
                            0
                        ],
                        "params": [
                            [
                                0.4557909961777886,
                                0.939640846838631,
                                0.8511951183924182,
                                0.9422932771196866
                            ]
                        ],
                        "grad": 4,
                        "sgn": 0
                    },
                    {
                        "Em": -3.8072826862335205,
                        "num_trials": 0,
                        "post-processed": [
                            0
                        ],
                        "params": [
                            [
                                0.35078384521062883,
                                0.8346336958714712,
                                0.9562022693595781,
                                0.8372861261525267
                            ]
                        ],
                        "grad": 5,
                        "sgn": 0
                    },
                    {
                        "Em": -3.7802681922912598,
                        "num_trials": 0,
                        "post-processed": [
                            0
                        ],
                        "params": [
                            [
                                0.387691322624682,
                                0.797726218457418,
                                0.9192947919455249,
                                0.8741936035665799
                            ]
                        ],
                        "grad": 6,
                        "sgn": 0
                    },
                    {
                        "Em": -3.7964107990264893,
                        "num_trials": 0,
                        "post-processed": [
                            0
                        ],
                        "params": [
                            [
                                0.36596908334242495,
                                0.776003979175161,
                                0.9410170312277819,
                                0.8524713642843229
                            ]
                        ],
                        "grad": 7,
                        "sgn": 0
                    },
                    {
                        "Em": -3.791835308074951,
                        "num_trials": 0,
                        "post-processed": [
                            0
                        ],
                        "params": [
                            [
                                0.3770148636259442,
                                0.7870497594586802,
                                0.9299712509442627,
                                0.8414255840008037
                            ]
                        ],
                        "grad": 8,
                        "sgn": 0
                    },
                    {
                        "Em": -3.762850761413574,
                        "num_trials": 0,
                        "post-processed": [
                            0
                        ],
                        "params": [
                            [
                                0.41445659003579294,
                                0.7496080330488314,
                                0.8925295245344139,
                                0.8788673104106525
                            ]
                        ],
                        "grad": 9,
                        "sgn": 0
                    },
                    {
                        "Em": -3.798384666442871,
                        "num_trials": 0,
                        "post-processed": [
                            0
                        ],
                        "params": [
                            [
                                0.36686128767155374,
                                0.7020127306845921,
                                0.8449342221701747,
                                0.9264626127748917
                            ]
                        ],
                        "grad": 10,
                        "sgn": 0
                    },
                    {
                        "Em": -3.8393502235412598,
                        "num_trials": 0,
                        "post-processed": [
                            0
                        ],
                        "params": [
                            [
                                0.30539268415900866,
                                0.6405441271720471,
                                0.7834656186576296,
                                0.9879312162874367
                            ]
                        ],
                        "grad": 11,
                        "sgn": 0
                    },
                    {
                        "Em": -3.8294119834899902,
                        "num_trials": 0,
                        "post-processed": [
                            0
                        ],
                        "params": [
                            [
                                0.33513453666379694,
                                0.6702859796768355,
                                0.7537237661528413,
                                0.9581893637826484
                            ]
                        ],
                        "grad": 12,
                        "sgn": 0
                    },
                    {
                        "Em": -3.7955780029296875,
                        "num_trials": 0,
                        "post-processed": [
                            0
                        ],
                        "params": [
                            [
                                0.4062771793011849,
                                0.5991433370394476,
                                0.6825811235154534,
                                0.8870467211452605
                            ]
                        ],
                        "grad": 13,
                        "sgn": 0
                    },
                    {
                        "Em": -3.851548671722412,
                        "num_trials": 0,
                        "post-processed": [
                            0
                        ],
                        "params": [
                            [
                                0.3451094644389563,
                                0.537975622177219,
                                0.6214134086532248,
                                0.8258790062830319
                            ]
                        ],
                        "grad": 14,
                        "sgn": 0
                    }
                ],
                "vert02": [
                    {
                        "Em": -1.523000717163086,
                        "num_trials": 0,
                        "post-processed": [
                            0
                        ],
                        "params": [
                            [
                                0.8312871881382002,
                                1.1687128118617998,
                                0.8312871881382002,
                                1.1687128118617998
                            ]
                        ],
                        "grad": 0,
                        "sgn": 0
                    },
                    {
                        "Em": -1.4797017574310303,
                        "num_trials": 0,
                        "post-processed": [
                            0
                        ],
                        "params": [
                            [
                                0.6521668421445757,
                                0.9895924658681752,
                                1.0104075341318248,
                                1.3478331578554243
                            ]
                        ],
                        "grad": 1,
                        "sgn": 0
                    },
                    {
                        "Em": -1.511509656906128,
                        "num_trials": 0,
                        "post-processed": [
                            0
                        ],
                        "params": [
                            [
                                0.756748859529051,
                                0.8850104484836998,
                                0.9058255167473495,
                                1.243251140470949
                            ]
                        ],
                        "grad": 2,
                        "sgn": 0
                    },
                    {
                        "Em": -1.7337498664855957,
                        "num_trials": 0,
                        "post-processed": [
                            0
                        ],
                        "params": [
                            [
                                0.5789547286759542,
                                1.0628045793367966,
                                0.7280313858942526,
                                1.0654570096178522
                            ]
                        ],
                        "grad": 3,
                        "sgn": 0
                    },
                    {
                        "Em": -1.7993721961975098,
                        "num_trials": 0,
                        "post-processed": [
                            0
                        ],
                        "params": [
                            [
                                0.4557909961777886,
                                0.939640846838631,
                                0.8511951183924182,
                                0.9422932771196866
                            ]
                        ],
                        "grad": 4,
                        "sgn": 0
                    },
                    {
                        "Em": -1.838680624961853,
                        "num_trials": 0,
                        "post-processed": [
                            0
                        ],
                        "params": [
                            [
                                0.35078384521062883,
                                0.8346336958714712,
                                0.9562022693595781,
                                0.8372861261525267
                            ]
                        ],
                        "grad": 5,
                        "sgn": 0
                    },
                    {
                        "Em": -1.8266606330871582,
                        "num_trials": 0,
                        "post-processed": [
                            0
                        ],
                        "params": [
                            [
                                0.387691322624682,
                                0.797726218457418,
                                0.9192947919455249,
                                0.8741936035665799
                            ]
                        ],
                        "grad": 6,
                        "sgn": 0
                    },
                    {
                        "Em": -1.8339745998382568,
                        "num_trials": 0,
                        "post-processed": [
                            0
                        ],
                        "params": [
                            [
                                0.36596908334242495,
                                0.776003979175161,
                                0.9410170312277819,
                                0.8524713642843229
                            ]
                        ],
                        "grad": 7,
                        "sgn": 0
                    },
                    {
                        "Em": -1.8382395505905151,
                        "num_trials": 0,
                        "post-processed": [
                            0
                        ],
                        "params": [
                            [
                                0.3770148636259442,
                                0.7870497594586802,
                                0.9299712509442627,
                                0.8414255840008037
                            ]
                        ],
                        "grad": 8,
                        "sgn": 0
                    },
                    {
                        "Em": -1.824886679649353,
                        "num_trials": 0,
                        "post-processed": [
                            0
                        ],
                        "params": [
                            [
                                0.41445659003579294,
                                0.7496080330488314,
                                0.8925295245344139,
                                0.8788673104106525
                            ]
                        ],
                        "grad": 9,
                        "sgn": 0
                    },
                    {
                        "Em": -1.8386949300765991,
                        "num_trials": 0,
                        "post-processed": [
                            0
                        ],
                        "params": [
                            [
                                0.36686128767155374,
                                0.7020127306845921,
                                0.8449342221701747,
                                0.9264626127748917
                            ]
                        ],
                        "grad": 10,
                        "sgn": 0
                    },
                    {
                        "Em": -1.851365089416504,
                        "num_trials": 0,
                        "post-processed": [
                            0
                        ],
                        "params": [
                            [
                                0.30539268415900866,
                                0.6405441271720471,
                                0.7834656186576296,
                                0.9879312162874367
                            ]
                        ],
                        "grad": 11,
                        "sgn": 0
                    },
                    {
                        "Em": -1.864320993423462,
                        "num_trials": 0,
                        "post-processed": [
                            0
                        ],
                        "params": [
                            [
                                0.33513453666379694,
                                0.6702859796768355,
                                0.7537237661528413,
                                0.9581893637826484
                            ]
                        ],
                        "grad": 12,
                        "sgn": 0
                    },
                    {
                        "Em": -1.8890047073364258,
                        "num_trials": 0,
                        "post-processed": [
                            0
                        ],
                        "params": [
                            [
                                0.4062771793011849,
                                0.5991433370394476,
                                0.6825811235154534,
                                0.8870467211452605
                            ]
                        ],
                        "grad": 13,
                        "sgn": 0
                    },
                    {
                        "Em": -1.9476271867752075,
                        "num_trials": 0,
                        "post-processed": [
                            0
                        ],
                        "params": [
                            [
                                0.3451094644389563,
                                0.537975622177219,
                                0.6214134086532248,
                                0.8258790062830319
                            ]
                        ],
                        "grad": 14,
                        "sgn": 0
                    }
                ],
                "vert12": [
                    {
                        "Em": -2.1480627059936523,
                        "num_trials": 0,
                        "post-processed": [
                            0
                        ],
                        "params": [
                            [
                                0.8312871881382002,
                                1.1687128118617998,
                                0.8312871881382002,
                                1.1687128118617998
                            ]
                        ],
                        "grad": 0,
                        "sgn": 0
                    },
                    {
                        "Em": -2.3403806686401367,
                        "num_trials": 0,
                        "post-processed": [
                            0
                        ],
                        "params": [
                            [
                                0.6521668421445757,
                                0.9895924658681752,
                                1.0104075341318248,
                                1.3478331578554243
                            ]
                        ],
                        "grad": 1,
                        "sgn": 0
                    },
                    {
                        "Em": -2.233405351638794,
                        "num_trials": 0,
                        "post-processed": [
                            0
                        ],
                        "params": [
                            [
                                0.756748859529051,
                                0.8850104484836998,
                                0.9058255167473495,
                                1.243251140470949
                            ]
                        ],
                        "grad": 2,
                        "sgn": 0
                    },
                    {
                        "Em": -2.2951793670654297,
                        "num_trials": 0,
                        "post-processed": [
                            0
                        ],
                        "params": [
                            [
                                0.5789547286759542,
                                1.0628045793367966,
                                0.7280313858942526,
                                1.0654570096178522
                            ]
                        ],
                        "grad": 3,
                        "sgn": 0
                    },
                    {
                        "Em": -2.3827505111694336,
                        "num_trials": 0,
                        "post-processed": [
                            0
                        ],
                        "params": [
                            [
                                0.4557909961777886,
                                0.939640846838631,
                                0.8511951183924182,
                                0.9422932771196866
                            ]
                        ],
                        "grad": 4,
                        "sgn": 0
                    },
                    {
                        "Em": -2.4169769287109375,
                        "num_trials": 0,
                        "post-processed": [
                            0
                        ],
                        "params": [
                            [
                                0.35078384521062883,
                                0.8346336958714712,
                                0.9562022693595781,
                                0.8372861261525267
                            ]
                        ],
                        "grad": 5,
                        "sgn": 0
                    },
                    {
                        "Em": -2.409238576889038,
                        "num_trials": 0,
                        "post-processed": [
                            0
                        ],
                        "params": [
                            [
                                0.387691322624682,
                                0.797726218457418,
                                0.9192947919455249,
                                0.8741936035665799
                            ]
                        ],
                        "grad": 6,
                        "sgn": 0
                    },
                    {
                        "Em": -2.414358615875244,
                        "num_trials": 0,
                        "post-processed": [
                            0
                        ],
                        "params": [
                            [
                                0.36596908334242495,
                                0.776003979175161,
                                0.9410170312277819,
                                0.8524713642843229
                            ]
                        ],
                        "grad": 7,
                        "sgn": 0
                    },
                    {
                        "Em": -2.4058775901794434,
                        "num_trials": 0,
                        "post-processed": [
                            0
                        ],
                        "params": [
                            [
                                0.3770148636259442,
                                0.7870497594586802,
                                0.9299712509442627,
                                0.8414255840008037
                            ]
                        ],
                        "grad": 8,
                        "sgn": 0
                    },
                    {
                        "Em": -2.395509958267212,
                        "num_trials": 0,
                        "post-processed": [
                            0
                        ],
                        "params": [
                            [
                                0.41445659003579294,
                                0.7496080330488314,
                                0.8925295245344139,
                                0.8788673104106525
                            ]
                        ],
                        "grad": 9,
                        "sgn": 0
                    },
                    {
                        "Em": -2.4191253185272217,
                        "num_trials": 0,
                        "post-processed": [
                            0
                        ],
                        "params": [
                            [
                                0.36686128767155374,
                                0.7020127306845921,
                                0.8449342221701747,
                                0.9264626127748917
                            ]
                        ],
                        "grad": 10,
                        "sgn": 0
                    },
                    {
                        "Em": -2.4378013610839844,
                        "num_trials": 0,
                        "post-processed": [
                            0
                        ],
                        "params": [
                            [
                                0.30539268415900866,
                                0.6405441271720471,
                                0.7834656186576296,
                                0.9879312162874367
                            ]
                        ],
                        "grad": 11,
                        "sgn": 0
                    },
                    {
                        "Em": -2.4149107933044434,
                        "num_trials": 0,
                        "post-processed": [
                            0
                        ],
                        "params": [
                            [
                                0.33513453666379694,
                                0.6702859796768355,
                                0.7537237661528413,
                                0.9581893637826484
                            ]
                        ],
                        "grad": 12,
                        "sgn": 0
                    },
                    {
                        "Em": -2.3559794425964355,
                        "num_trials": 0,
                        "post-processed": [
                            0
                        ],
                        "params": [
                            [
                                0.4062771793011849,
                                0.5991433370394476,
                                0.6825811235154534,
                                0.8870467211452605
                            ]
                        ],
                        "grad": 13,
                        "sgn": 0
                    },
                    {
                        "Em": -2.3547751903533936,
                        "num_trials": 0,
                        "post-processed": [
                            0
                        ],
                        "params": [
                            [
                                0.3451094644389563,
                                0.537975622177219,
                                0.6214134086532248,
                                0.8258790062830319
                            ]
                        ],
                        "grad": 14,
                        "sgn": 0
                    }
                ],
                "all_E": {
                    "0": {
                        "0": -5.156678080558777
                    },
                    "1": {
                        "0": -5.484803080558777
                    },
                    "2": {
                        "0": -5.556284189224243
                    },
                    "3": {
                        "0": -6.037197709083557
                    },
                    "4": {
                        "0": -6.302040696144104
                    },
                    "5": {
                        "0": -6.408449649810791
                    },
                    "6": {
                        "0": -6.434470176696777
                    },
                    "7": {
                        "0": -6.446622848510742
                    },
                    "8": {
                        "0": -6.450981616973877
                    },
                    "9": {
                        "0": -6.477088451385498
                    },
                    "10": {
                        "0": -6.5507659912109375
                    },
                    "11": {
                        "0": -6.594611287117004
                    },
                    "12": {
                        "0": -6.624600172042847
                    },
                    "13": {
                        "0": -6.746664643287659
                    },
                    "14": {
                        "0": -6.823863863945007
                    }
                },
                "start_timestamp": "2021-09-20 11:03:33.824432",
                "end_timestamp": "2021-09-20 11:03:57.987775",
                "E": [
                    -5.156678080558777,
                    -5.484803080558777,
                    -5.556284189224243,
                    -6.037197709083557,
                    -6.302040696144104,
                    -6.408449649810791,
                    -6.434470176696777,
                    -6.446622848510742,
                    -6.450981616973877,
                    -6.477088451385498,
                    -6.5507659912109375,
                    -6.594611287117004,
                    -6.624600172042847,
                    -6.746664643287659,
                    -6.823863863945007
                ],
                "E_list": [
                    -5.156678080558777,
                    -5.484803080558777,
                    -5.556284189224243,
                    -6.037197709083557,
                    -6.302040696144104,
                    -6.408449649810791,
                    -6.434470176696777,
                    -6.446622848510742,
                    -6.450981616973877,
                    -6.477088451385498,
                    -6.5507659912109375,
                    -6.594611287117004,
                    -6.624600172042847,
                    -6.746664643287659,
                    -6.823863863945007
                ]
            }
        ],
        [
            -5.156678080558777,
            -5.484803080558777,
            -5.556284189224243,
            -6.037197709083557,
            -6.302040696144104,
            -6.408449649810791,
            -6.434470176696777,
            -6.446622848510742,
            -6.450981616973877,
            -6.477088451385498,
            -6.5507659912109375,
            -6.594611287117004,
            -6.624600172042847,
            -6.746664643287659,
            -6.823863863945007
        ],
        [
            [
                [
                    [
                        0.8312871881382002,
                        1.1687128118617998,
                        0.8312871881382002,
                        1.1687128118617998
                    ]
                ]
            ],
            [
                [
                    [
                        0.6521668421445757,
                        0.9895924658681752,
                        1.0104075341318248,
                        1.3478331578554243
                    ]
                ]
            ],
            [
                [
                    [
                        0.756748859529051,
                        0.8850104484836998,
                        0.9058255167473495,
                        1.243251140470949
                    ]
                ]
            ],
            [
                [
                    [
                        0.5789547286759542,
                        1.0628045793367966,
                        0.7280313858942526,
                        1.0654570096178522
                    ]
                ]
            ],
            [
                [
                    [
                        0.4557909961777886,
                        0.939640846838631,
                        0.8511951183924182,
                        0.9422932771196866
                    ]
                ]
            ],
            [
                [
                    [
                        0.35078384521062883,
                        0.8346336958714712,
                        0.9562022693595781,
                        0.8372861261525267
                    ]
                ]
            ],
            [
                [
                    [
                        0.387691322624682,
                        0.797726218457418,
                        0.9192947919455249,
                        0.8741936035665799
                    ]
                ]
            ],
            [
                [
                    [
                        0.36596908334242495,
                        0.776003979175161,
                        0.9410170312277819,
                        0.8524713642843229
                    ]
                ]
            ],
            [
                [
                    [
                        0.3770148636259442,
                        0.7870497594586802,
                        0.9299712509442627,
                        0.8414255840008037
                    ]
                ]
            ],
            [
                [
                    [
                        0.41445659003579294,
                        0.7496080330488314,
                        0.8925295245344139,
                        0.8788673104106525
                    ]
                ]
            ],
            [
                [
                    [
                        0.36686128767155374,
                        0.7020127306845921,
                        0.8449342221701747,
                        0.9264626127748917
                    ]
                ]
            ],
            [
                [
                    [
                        0.30539268415900866,
                        0.6405441271720471,
                        0.7834656186576296,
                        0.9879312162874367
                    ]
                ]
            ],
            [
                [
                    [
                        0.33513453666379694,
                        0.6702859796768355,
                        0.7537237661528413,
                        0.9581893637826484
                    ]
                ]
            ],
            [
                [
                    [
                        0.4062771793011849,
                        0.5991433370394476,
                        0.6825811235154534,
                        0.8870467211452605
                    ]
                ]
            ],
            [
                [
                    [
                        0.3451094644389563,
                        0.537975622177219,
                        0.6214134086532248,
                        0.8258790062830319
                    ]
                ]
            ]
        ],
        0
    ]
]