[
    [
        [
            [
                1.0,
                1.0,
                1.0,
                1.0
            ]
        ],
        28.681000883272148,
        [
            {
                "onsite0": [
                    {
                        "Em": 33.88185255198488,
                        "num_trials": 100000,
                        "post-processed": 16928,
                        "params": [
                            [
                                0.723,
                                0.474,
                                0.549,
                                0.253
                            ]
                        ],
                        "grad": 0,
                        "sgn": 0
                    },
                    {
                        "Em": 34.16180819602873,
                        "num_trials": 100000,
                        "post-processed": 18936,
                        "params": [
                            [
                                -0.723,
                                -0.474,
                                -0.549,
                                -0.253
                            ]
                        ],
                        "grad": 1,
                        "sgn": 0
                    },
                    {
                        "Em": 35.756221552284686,
                        "num_trials": 100000,
                        "post-processed": 16917,
                        "params": [
                            [
                                0.0,
                                0.474,
                                0.549,
                                0.253
                            ]
                        ],
                        "grad": 2,
                        "sgn": 0
                    },
                    {
                        "Em": 36.27109199927321,
                        "num_trials": 100000,
                        "post-processed": 16511,
                        "params": [
                            [
                                0.0,
                                -0.474,
                                -0.549,
                                -0.253
                            ]
                        ],
                        "grad": 3,
                        "sgn": 0
                    }
                ],
                "horiz0": [
                    {
                        "Em": -2.328589230668328,
                        "num_trials": 100000,
                        "post-processed": 15247,
                        "params": [
                            [
                                0.723,
                                0.474,
                                0.549,
                                0.253
                            ]
                        ],
                        "grad": 0,
                        "sgn": 0
                    },
                    {
                        "Em": -2.970473101442791,
                        "num_trials": 100000,
                        "post-processed": 17882,
                        "params": [
                            [
                                -0.723,
                                -0.474,
                                -0.549,
                                -0.253
                            ]
                        ],
                        "grad": 1,
                        "sgn": 0
                    },
                    {
                        "Em": -2.988893940377996,
                        "num_trials": 100000,
                        "post-processed": 15397,
                        "params": [
                            [
                                0.0,
                                0.474,
                                0.549,
                                0.253
                            ]
                        ],
                        "grad": 2,
                        "sgn": 0
                    },
                    {
                        "Em": -2.980238188718754,
                        "num_trials": 100000,
                        "post-processed": 15282,
                        "params": [
                            [
                                0.0,
                                -0.474,
                                -0.549,
                                -0.253
                            ]
                        ],
                        "grad": 3,
                        "sgn": 0
                    }
                ],
                "vert02": [
                    {
                        "Em": -1.4101719012537162,
                        "num_trials": 100000,
                        "post-processed": 15474,
                        "params": [
                            [
                                0.723,
                                0.474,
                                0.549,
                                0.253
                            ]
                        ],
                        "grad": 0,
                        "sgn": 0
                    },
                    {
                        "Em": -1.4947493133717484,
                        "num_trials": 100000,
                        "post-processed": 18569,
                        "params": [
                            [
                                -0.723,
                                -0.474,
                                -0.549,
                                -0.253
                            ]
                        ],
                        "grad": 1,
                        "sgn": 0
                    },
                    {
                        "Em": -1.6096707285455016,
                        "num_trials": 100000,
                        "post-processed": 15428,
                        "params": [
                            [
                                0.0,
                                0.474,
                                0.549,
                                0.253
                            ]
                        ],
                        "grad": 2,
                        "sgn": 0
                    },
                    {
                        "Em": -1.561660178324752,
                        "num_trials": 100000,
                        "post-processed": 15926,
                        "params": [
                            [
                                0.0,
                                -0.474,
                                -0.549,
                                -0.253
                            ]
                        ],
                        "grad": 3,
                        "sgn": 0
                    }
                ],
                "vert12": [
                    {
                        "Em": -1.1908218822919365,
                        "num_trials": 100000,
                        "post-processed": 15428,
                        "params": [
                            [
                                0.723,
                                0.474,
                                0.549,
                                0.253
                            ]
                        ],
                        "grad": 0,
                        "sgn": 0
                    },
                    {
                        "Em": -1.2868535524407927,
                        "num_trials": 100000,
                        "post-processed": 16552,
                        "params": [
                            [
                                -0.723,
                                -0.474,
                                -0.549,
                                -0.253
                            ]
                        ],
                        "grad": 1,
                        "sgn": 0
                    },
                    {
                        "Em": -1.5074206274657151,
                        "num_trials": 100000,
                        "post-processed": 15969,
                        "params": [
                            [
                                0.0,
                                0.474,
                                0.549,
                                0.253
                            ]
                        ],
                        "grad": 2,
                        "sgn": 0
                    },
                    {
                        "Em": -1.5014807502467917,
                        "num_trials": 100000,
                        "post-processed": 15195,
                        "params": [
                            [
                                0.0,
                                -0.474,
                                -0.549,
                                -0.253
                            ]
                        ],
                        "grad": 3,
                        "sgn": 0
                    }
                ],
                "all_E": {
                    "0": {
                        "0": 28.9522695377709
                    },
                    "1": {
                        "0": 28.409732228773397
                    },
                    "2": {
                        "0": 29.650236255895468
                    },
                    "3": {
                        "0": 30.227712881982917
                    }
                },
                "start_timestamp": "2021-09-19 22:28:23.156293",
                "end_timestamp": "2021-09-19 22:29:39.876795",
                "program_id": "4x2_single_U_8_nocc_12_d_1-0919-222806-222823-156346",
                "job_id": "4x2_single_U_8_nocc_12_d_1-0919-222806",
                "E": 28.681000883272148,
                "E_list": [
                    28.9522695377709,
                    28.409732228773397,
                    29.650236255895468,
                    30.227712881982917
                ]
            }
        ],
        [
            28.681000883272148
        ],
        [
            [
                [
                    [
                        0.723,
                        0.474,
                        0.549,
                        0.253
                    ]
                ]
            ],
            [
                [
                    [
                        -0.723,
                        -0.474,
                        -0.549,
                        -0.253
                    ]
                ]
            ],
            [
                [
                    [
                        0,
                        0.474,
                        0.549,
                        0.253
                    ]
                ]
            ],
            [
                [
                    [
                        0,
                        -0.474,
                        -0.549,
                        -0.253
                    ]
                ]
            ]
        ],
        0
    ]
]