[
    [
        [
            [
                1.0,
                1.0,
                1.0,
                1.0
            ]
        ],
        -4.686495000000001,
        [
            {
                "onsite0": [
                    {
                        "Em": 0.45748,
                        "num_trials": 100000,
                        "post-processed": 100000,
                        "params": [
                            [
                                0.295,
                                0.76,
                                0.672,
                                0.638
                            ]
                        ],
                        "grad": 0,
                        "sgn": 0
                    },
                    {
                        "Em": 0.45439999999999997,
                        "num_trials": 100000,
                        "post-processed": 100000,
                        "params": [
                            [
                                -0.295,
                                -0.76,
                                -0.672,
                                -0.638
                            ]
                        ],
                        "grad": 1,
                        "sgn": 0
                    },
                    {
                        "Em": 0.60056,
                        "num_trials": 100000,
                        "post-processed": 100000,
                        "params": [
                            [
                                0.0,
                                0.76,
                                0.672,
                                0.638
                            ]
                        ],
                        "grad": 2,
                        "sgn": 0
                    },
                    {
                        "Em": 0.59456,
                        "num_trials": 100000,
                        "post-processed": 100000,
                        "params": [
                            [
                                0.0,
                                -0.76,
                                -0.672,
                                -0.638
                            ]
                        ],
                        "grad": 3,
                        "sgn": 0
                    }
                ],
                "horiz0": [
                    {
                        "Em": -1.96616,
                        "num_trials": 100000,
                        "post-processed": 100000,
                        "params": [
                            [
                                0.295,
                                0.76,
                                0.672,
                                0.638
                            ]
                        ],
                        "grad": 0,
                        "sgn": 0
                    },
                    {
                        "Em": -1.96272,
                        "num_trials": 100000,
                        "post-processed": 100000,
                        "params": [
                            [
                                -0.295,
                                -0.76,
                                -0.672,
                                -0.638
                            ]
                        ],
                        "grad": 1,
                        "sgn": 0
                    },
                    {
                        "Em": -1.98886,
                        "num_trials": 100000,
                        "post-processed": 100000,
                        "params": [
                            [
                                0.0,
                                0.76,
                                0.672,
                                0.638
                            ]
                        ],
                        "grad": 2,
                        "sgn": 0
                    },
                    {
                        "Em": -1.98864,
                        "num_trials": 100000,
                        "post-processed": 100000,
                        "params": [
                            [
                                0.0,
                                -0.76,
                                -0.672,
                                -0.638
                            ]
                        ],
                        "grad": 3,
                        "sgn": 0
                    }
                ],
                "vert02": [
                    {
                        "Em": -1.5002900000000001,
                        "num_trials": 100000,
                        "post-processed": 100000,
                        "params": [
                            [
                                0.295,
                                0.76,
                                0.672,
                                0.638
                            ]
                        ],
                        "grad": 0,
                        "sgn": 0
                    },
                    {
                        "Em": -1.50635,
                        "num_trials": 100000,
                        "post-processed": 100000,
                        "params": [
                            [
                                -0.295,
                                -0.76,
                                -0.672,
                                -0.638
                            ]
                        ],
                        "grad": 1,
                        "sgn": 0
                    },
                    {
                        "Em": -1.5269599999999999,
                        "num_trials": 100000,
                        "post-processed": 100000,
                        "params": [
                            [
                                0.0,
                                0.76,
                                0.672,
                                0.638
                            ]
                        ],
                        "grad": 2,
                        "sgn": 0
                    },
                    {
                        "Em": -1.52029,
                        "num_trials": 100000,
                        "post-processed": 100000,
                        "params": [
                            [
                                0.0,
                                -0.76,
                                -0.672,
                                -0.638
                            ]
                        ],
                        "grad": 3,
                        "sgn": 0
                    }
                ],
                "vert12": [
                    {
                        "Em": -1.67439,
                        "num_trials": 100000,
                        "post-processed": 100000,
                        "params": [
                            [
                                0.295,
                                0.76,
                                0.672,
                                0.638
                            ]
                        ],
                        "grad": 0,
                        "sgn": 0
                    },
                    {
                        "Em": -1.6749600000000002,
                        "num_trials": 100000,
                        "post-processed": 100000,
                        "params": [
                            [
                                -0.295,
                                -0.76,
                                -0.672,
                                -0.638
                            ]
                        ],
                        "grad": 1,
                        "sgn": 0
                    },
                    {
                        "Em": -1.6989599999999998,
                        "num_trials": 100000,
                        "post-processed": 100000,
                        "params": [
                            [
                                0.0,
                                0.76,
                                0.672,
                                0.638
                            ]
                        ],
                        "grad": 2,
                        "sgn": 0
                    },
                    {
                        "Em": -1.69941,
                        "num_trials": 100000,
                        "post-processed": 100000,
                        "params": [
                            [
                                0.0,
                                -0.76,
                                -0.672,
                                -0.638
                            ]
                        ],
                        "grad": 3,
                        "sgn": 0
                    }
                ],
                "all_E": {
                    "0": {
                        "0": -4.68336
                    },
                    "1": {
                        "0": -4.68963
                    },
                    "2": {
                        "0": -4.6142199999999995
                    },
                    "3": {
                        "0": -4.61378
                    }
                },
                "start_timestamp": "2021-12-11 21:39:00.840449",
                "end_timestamp": "2021-12-11 21:39:39.638521",
                "E": -4.686495000000001,
                "E_list": [
                    -4.68336,
                    -4.68963,
                    -4.6142199999999995,
                    -4.61378
                ]
            }
        ],
        [
            -4.686495000000001
        ],
        [
            [
                [
                    [
                        0.295,
                        0.76,
                        0.672,
                        0.638
                    ]
                ]
            ],
            [
                [
                    [
                        -0.295,
                        -0.76,
                        -0.672,
                        -0.638
                    ]
                ]
            ],
            [
                [
                    [
                        0,
                        0.76,
                        0.672,
                        0.638
                    ]
                ]
            ],
            [
                [
                    [
                        0,
                        -0.76,
                        -0.672,
                        -0.638
                    ]
                ]
            ]
        ],
        0
    ]
]