[
    [
        [
            [
                1.0,
                1.0,
                1.0,
                1.0
            ]
        ],
        6.379659395716356,
        [
            {
                "onsite0": [
                    {
                        "Em": 11.809960886571057,
                        "num_trials": 100000,
                        "post-processed": 19175,
                        "params": [
                            [
                                0.527,
                                0.279,
                                0.628,
                                0.618
                            ]
                        ],
                        "grad": 0,
                        "sgn": 0
                    },
                    {
                        "Em": 11.528072914044012,
                        "num_trials": 100000,
                        "post-processed": 19859,
                        "params": [
                            [
                                -0.527,
                                -0.279,
                                -0.628,
                                -0.618
                            ]
                        ],
                        "grad": 1,
                        "sgn": 0
                    },
                    {
                        "Em": 13.079975947083586,
                        "num_trials": 100000,
                        "post-processed": 19956,
                        "params": [
                            [
                                0.0,
                                0.279,
                                0.628,
                                0.618
                            ]
                        ],
                        "grad": 2,
                        "sgn": 0
                    },
                    {
                        "Em": 12.659336184076563,
                        "num_trials": 100000,
                        "post-processed": 19644,
                        "params": [
                            [
                                0.0,
                                -0.279,
                                -0.628,
                                -0.618
                            ]
                        ],
                        "grad": 3,
                        "sgn": 0
                    }
                ],
                "horiz0": [
                    {
                        "Em": -1.235141828005403,
                        "num_trials": 100000,
                        "post-processed": 17768,
                        "params": [
                            [
                                0.527,
                                0.279,
                                0.628,
                                0.618
                            ]
                        ],
                        "grad": 0,
                        "sgn": 0
                    },
                    {
                        "Em": -1.4969193950812159,
                        "num_trials": 100000,
                        "post-processed": 19639,
                        "params": [
                            [
                                -0.527,
                                -0.279,
                                -0.628,
                                -0.618
                            ]
                        ],
                        "grad": 1,
                        "sgn": 0
                    },
                    {
                        "Em": -1.4643623872906826,
                        "num_trials": 100000,
                        "post-processed": 18632,
                        "params": [
                            [
                                0.0,
                                0.279,
                                0.628,
                                0.618
                            ]
                        ],
                        "grad": 2,
                        "sgn": 0
                    },
                    {
                        "Em": -1.4872010071338648,
                        "num_trials": 100000,
                        "post-processed": 19064,
                        "params": [
                            [
                                0.0,
                                -0.279,
                                -0.628,
                                -0.618
                            ]
                        ],
                        "grad": 3,
                        "sgn": 0
                    }
                ],
                "vert02": [
                    {
                        "Em": -2.080470840021402,
                        "num_trials": 100000,
                        "post-processed": 18690,
                        "params": [
                            [
                                0.527,
                                0.279,
                                0.628,
                                0.618
                            ]
                        ],
                        "grad": 0,
                        "sgn": 0
                    },
                    {
                        "Em": -1.9277844551282053,
                        "num_trials": 100000,
                        "post-processed": 19968,
                        "params": [
                            [
                                -0.527,
                                -0.279,
                                -0.628,
                                -0.618
                            ]
                        ],
                        "grad": 1,
                        "sgn": 0
                    },
                    {
                        "Em": -2.2141008714021653,
                        "num_trials": 100000,
                        "post-processed": 18935,
                        "params": [
                            [
                                0.0,
                                0.279,
                                0.628,
                                0.618
                            ]
                        ],
                        "grad": 2,
                        "sgn": 0
                    },
                    {
                        "Em": -2.0846354833751732,
                        "num_trials": 100000,
                        "post-processed": 19519,
                        "params": [
                            [
                                0.0,
                                -0.279,
                                -0.628,
                                -0.618
                            ]
                        ],
                        "grad": 3,
                        "sgn": 0
                    }
                ],
                "vert12": [
                    {
                        "Em": -1.8387243476777897,
                        "num_trials": 100000,
                        "post-processed": 17591,
                        "params": [
                            [
                                0.527,
                                0.279,
                                0.628,
                                0.618
                            ]
                        ],
                        "grad": 0,
                        "sgn": 0
                    },
                    {
                        "Em": -1.999674143268343,
                        "num_trials": 100000,
                        "post-processed": 18413,
                        "params": [
                            [
                                -0.527,
                                -0.279,
                                -0.628,
                                -0.618
                            ]
                        ],
                        "grad": 1,
                        "sgn": 0
                    },
                    {
                        "Em": -1.9585980162710355,
                        "num_trials": 100000,
                        "post-processed": 17946,
                        "params": [
                            [
                                0.0,
                                0.279,
                                0.628,
                                0.618
                            ]
                        ],
                        "grad": 2,
                        "sgn": 0
                    },
                    {
                        "Em": -2.108888141672271,
                        "num_trials": 100000,
                        "post-processed": 17844,
                        "params": [
                            [
                                0.0,
                                -0.279,
                                -0.628,
                                -0.618
                            ]
                        ],
                        "grad": 3,
                        "sgn": 0
                    }
                ],
                "all_E": {
                    "0": {
                        "0": 6.655623870866462
                    },
                    "1": {
                        "0": 6.103694920566249
                    },
                    "2": {
                        "0": 7.442914672119703
                    },
                    "3": {
                        "0": 6.978611551895256
                    }
                },
                "start_timestamp": "2021-09-15 22:18:59.233995",
                "end_timestamp": "2021-09-15 22:20:11.811682",
                "program_id": "4x2_single_U_4_nocc_10_d_1-0915-221840-221859-234045",
                "job_id": "4x2_single_U_4_nocc_10_d_1-0915-221840",
                "E": 6.379659395716356,
                "E_list": [
                    6.655623870866462,
                    6.103694920566249,
                    7.442914672119703,
                    6.978611551895256
                ]
            }
        ],
        [
            6.379659395716356
        ],
        [
            [
                [
                    [
                        0.527,
                        0.279,
                        0.628,
                        0.618
                    ]
                ]
            ],
            [
                [
                    [
                        -0.527,
                        -0.279,
                        -0.628,
                        -0.618
                    ]
                ]
            ],
            [
                [
                    [
                        0,
                        0.279,
                        0.628,
                        0.618
                    ]
                ]
            ],
            [
                [
                    [
                        0,
                        -0.279,
                        -0.628,
                        -0.618
                    ]
                ]
            ]
        ],
        0
    ]
]